README.md
setup.py
dsh_envelope/__init__.py
dsh_envelope/envelope_pb2.py
dsh_envelope/protobuf.py
kpn_dsh_mqtt_envelope.egg-info/PKG-INFO
kpn_dsh_mqtt_envelope.egg-info/SOURCES.txt
kpn_dsh_mqtt_envelope.egg-info/dependency_links.txt
kpn_dsh_mqtt_envelope.egg-info/not-zip-safe
kpn_dsh_mqtt_envelope.egg-info/requires.txt
kpn_dsh_mqtt_envelope.egg-info/top_level.txt