Metadata-Version: 2.1
Name: kpn-dsh-mqtt-envelope
Version: 0.2.3
Summary: Envelope wrapper/unwrap for kpn-dsh-mqtt-envelopes
Home-page: https://github.com/bkasap/kpn-dsh-mqtt-envelope
Author: Bahadir Kasap
Author-email: bkasap@gmail.com
License: UNKNOWN
Platform: UNKNOWN
Classifier: Programming Language :: Python :: 3
Classifier: License :: OSI Approved :: MIT License
Classifier: Operating System :: OS Independent
Requires-Python: >=2.7
